par_infini_sweeper/__init__.py
par_infini_sweeper/__main__.py
par_infini_sweeper/auth.py
par_infini_sweeper/data_structures.py
par_infini_sweeper/db.py
par_infini_sweeper/db_migrations.py
par_infini_sweeper/enums.py
par_infini_sweeper/help.md
par_infini_sweeper/main_grid.py
par_infini_sweeper/messages.py
par_infini_sweeper/models.py
par_infini_sweeper/pim.tcss
par_infini_sweeper/pim_app.py
par_infini_sweeper/py.typed
par_infini_sweeper/utils.py
par_infini_sweeper/dialogs/__init__.py
par_infini_sweeper/dialogs/difficulty_dialog.py
par_infini_sweeper/dialogs/error_dialog.py
par_infini_sweeper/dialogs/help_dialog.py
par_infini_sweeper/dialogs/highscore_dialog.py
par_infini_sweeper/dialogs/information.py
par_infini_sweeper/dialogs/input_dialog.py
par_infini_sweeper/dialogs/login_dialog.py
par_infini_sweeper/dialogs/password_dialog.py
par_infini_sweeper/dialogs/text_dialog.py
par_infini_sweeper/dialogs/theme_dialog.py
par_infini_sweeper/dialogs/url_dialog.py
par_infini_sweeper/dialogs/yes_no_dialog.py
par_infini_sweeper-0.3.7.dist-info/METADATA
par_infini_sweeper-0.3.7.dist-info/WHEEL
par_infini_sweeper-0.3.7.dist-info/entry_points.txt
par_infini_sweeper-0.3.7.dist-info/licenses/LICENSE
par_infini_sweeper-0.3.7.dist-info/RECORD
