Metadata-Version: 2.4
Name: par_infini_sweeper
Version: 0.3.7
Summary: Par Infinite Minesweeper
Project-URL: Homepage, https://github.com/paulrobello/par_infini_sweeper
Project-URL: Documentation, https://github.com/paulrobello/par_infini_sweeper/blob/main/README.md
Project-URL: Repository, https://github.com/paulrobello/par_infini_sweeper
Project-URL: Issues, https://github.com/paulrobello/par_infini_sweeper/issues
Project-URL: Discussions, https://github.com/paulrobello/par_infini_sweeper/discussions
Project-URL: Wiki, https://github.com/paulrobello/par_infini_sweeper/wiki
Author-email: Paul Robello <probello@gmail.com>
Maintainer-email: Paul Robello <probello@gmail.com>
License: MIT License
License-File: LICENSE
Keywords: minesweeper,terminal,tui
Classifier: Development Status :: 4 - Beta
Classifier: Environment :: Console
Classifier: Intended Audience :: Developers
Classifier: Intended Audience :: End Users/Desktop
Classifier: Intended Audience :: Other Audience
Classifier: License :: OSI Approved :: MIT License
Classifier: Operating System :: MacOS
Classifier: Operating System :: Microsoft :: Windows :: Windows 10
Classifier: Operating System :: Microsoft :: Windows :: Windows 11
Classifier: Operating System :: POSIX :: Linux
Classifier: Programming Language :: Python :: 3
Classifier: Programming Language :: Python :: 3.11
Classifier: Programming Language :: Python :: 3.12
Classifier: Programming Language :: Python :: 3.13
Classifier: Topic :: Software Development :: Libraries :: Python Modules
Classifier: Typing :: Typed
Requires-Python: >=3.11
Requires-Dist: authlib>=1.6.1
Requires-Dist: orjson>=3.11.2
Requires-Dist: pydantic>=2.11.1
Requires-Dist: python-dotenv>=1.1.1
Requires-Dist: python-jose>=3.5.0
Requires-Dist: requests>=2.32.4
Requires-Dist: rich>=14.1.0
Requires-Dist: textual-serve>=1.1.2
Requires-Dist: textual>=5.3.0
Requires-Dist: typer>=0.16.0
Requires-Dist: xdg-base-dirs>=6.0.2
